pg_mcp/__init__.py
pg_mcp/bind_params.py
pg_mcp/env_utils.py
pg_mcp/extension_utils.py
pg_mcp/safe_sql.py
pg_mcp/server.py
pg_mcp/sql_driver.py
pg_mcp-0.2.1.dist-info/METADATA
pg_mcp-0.2.1.dist-info/WHEEL
pg_mcp-0.2.1.dist-info/entry_points.txt
pg_mcp-0.2.1.dist-info/licenses/LICENSE
pg_mcp-0.2.1.dist-info/RECORD
