Metadata-Version: 2.4
Name: pg-mcp
Version: 0.2.1
Summary: A lightweight, read-only-by-default PostgreSQL MCP server for data analysts and ETL developers
Project-URL: Homepage, https://github.com/andre-c-andersen/pg-mcp
Project-URL: Repository, https://github.com/andre-c-andersen/pg-mcp
Project-URL: Issues, https://github.com/andre-c-andersen/pg-mcp/issues
Project-URL: Original Project, https://github.com/crystaldba/postgres-mcp
Author-email: "André C. Andersen" <andre@andersen.im>
License: MIT
License-File: LICENSE
Keywords: ai,database,llm,mcp,model-context-protocol,postgres,postgresql
Classifier: Development Status :: 4 - Beta
Classifier: Intended Audience :: Developers
Classifier: License :: OSI Approved :: MIT License
Classifier: Programming Language :: Python :: 3
Classifier: Programming Language :: Python :: 3.12
Classifier: Topic :: Database
Classifier: Topic :: Software Development :: Libraries :: Python Modules
Requires-Python: >=3.12
Requires-Dist: attrs>=25.3.0
Requires-Dist: humanize>=4.8.0
Requires-Dist: instructor>=1.7.9
Requires-Dist: mcp[cli]>=1.5.0
Requires-Dist: pglast==7.2.0
Requires-Dist: psycopg[binary]>=3.2.6
